LICENSE
README.md
setup.py
macros/__init__.py
macros/macros.py
macros.py.egg-info/PKG-INFO
macros.py.egg-info/SOURCES.txt
macros.py.egg-info/dependency_links.txt
macros.py.egg-info/requires.txt
macros.py.egg-info/top_level.txt