Metadata-Version: 2.1
Name: macros.py
Version: 0.2.0
Summary: Macros for Python
Home-page: https://github.com/spookybear0/macros.py
Author: spookybear0
Author-email: collinmcarroll@gmail.com
License: MIT
Project-URL: Issue tracker, https://github.com/spookybear0/macros.py/issues
Platform: UNKNOWN
Requires-Python: >=3.5
License-File: LICENSE
